Mopidy_Radio_Rough-3.14.15.dist-info/DESCRIPTION.rst
Mopidy_Radio_Rough-3.14.15.dist-info/METADATA
Mopidy_Radio_Rough-3.14.15.dist-info/RECORD
Mopidy_Radio_Rough-3.14.15.dist-info/WHEEL
Mopidy_Radio_Rough-3.14.15.dist-info/entry_points.txt
Mopidy_Radio_Rough-3.14.15.dist-info/metadata.json
Mopidy_Radio_Rough-3.14.15.dist-info/top_level.txt
mopidy_radio_rough/__init__.py
mopidy_radio_rough/ext.conf
mopidy_radio_rough/mopidy_radio_rough.py
mopidy_radio_rough/radio_rough.desktop
mopidy_radio_rough/rough.py
mopidy_radio_rough/search_dialog.py
mopidy_radio_rough/tooltip.py
mopidy_radio_rough/ucc.gif
mopidy_radio_rough/ucc.png
mopidy_radio_rough/ucc_64.png
