Metadata-Version: 2.0
Name: Mopidy-Radio-Rough
Version: 3.14.15
Summary: Rough gui for listening to internet
Home-page: https://github.com/unusualcomputers/unusualcomputers/tree/master/code/mopidy/mopidyradiorough
Author: Unusual Computers
Author-email: unusual.computers@gmail.com
License: Apache License, Version 2.0
Platform: UNKNOWN
Classifier: Environment :: No Input/Output (Daemon)
Classifier: Intended Audience :: End Users/Desktop
Classifier: License :: OSI Approved :: Apache Software License
Classifier: Operating System :: OS Independent
Classifier: Programming Language :: Python :: 2
Classifier: Topic :: Multimedia :: Sound/Audio :: Players
Requires-Dist: Mopidy (>=1.0)
Requires-Dist: Mopidy-Mixcloud
Requires-Dist: Mopidy-Podcast-iTunes
Requires-Dist: Mopidy-Rough-Base (>=3.14.15)
Requires-Dist: Mopidy-TuneIn
Requires-Dist: Mopidy-Youtube
Requires-Dist: Pykka (>=1.1)
Requires-Dist: feedparser
Requires-Dist: jsonpickle
Requires-Dist: mutagen
Requires-Dist: setuptools
